narp_functions/__init__.py
narp_functions/integrator.py
narp_functions/narp_functions.py
narp_functions/pulses.py
narp_dynamics-1.4.dist-info/METADATA
narp_dynamics-1.4.dist-info/WHEEL
narp_dynamics-1.4.dist-info/top_level.txt
narp_dynamics-1.4.dist-info/RECORD
